CHANGES.rst
CONTRIBUTORS.rst
LICENSE.GPL
LICENSE.rst
MANIFEST.in
README.rst
requirements.txt
setup.cfg
setup.py
docs/LICENSE.GPL
docs/LICENSE.rst
docs/index.rst
src/collective/__init__.py
src/collective.contentrules.mustread.egg-info/PKG-INFO
src/collective.contentrules.mustread.egg-info/SOURCES.txt
src/collective.contentrules.mustread.egg-info/dependency_links.txt
src/collective.contentrules.mustread.egg-info/entry_points.txt
src/collective.contentrules.mustread.egg-info/namespace_packages.txt
src/collective.contentrules.mustread.egg-info/not-zip-safe
src/collective.contentrules.mustread.egg-info/requires.txt
src/collective.contentrules.mustread.egg-info/top_level.txt
src/collective/contentrules/__init__.py
src/collective/contentrules/mustread/__init__.py
src/collective/contentrules/mustread/archetypes.zcml
src/collective/contentrules/mustread/config.py
src/collective/contentrules/mustread/configure.zcml
src/collective/contentrules/mustread/event.py
src/collective/contentrules/mustread/interfaces.py
src/collective/contentrules/mustread/permissions.zcml
src/collective/contentrules/mustread/setuphandlers.py
src/collective/contentrules/mustread/stringinterp.py
src/collective/contentrules/mustread/testing.py
src/collective/contentrules/mustread/actions/__init__.py
src/collective/contentrules/mustread/actions/configure.zcml
src/collective/contentrules/mustread/actions/mail.py
src/collective/contentrules/mustread/actions/vocabularies.py
src/collective/contentrules/mustread/browser/__init__.py
src/collective/contentrules/mustread/browser/configure.zcml
src/collective/contentrules/mustread/browser/expired_email.pt
src/collective/contentrules/mustread/browser/stats.py
src/collective/contentrules/mustread/browser/views.py
src/collective/contentrules/mustread/locales/collective.contentrules.mustread.pot
src/collective/contentrules/mustread/locales/plone.pot
src/collective/contentrules/mustread/locales/update.sh
src/collective/contentrules/mustread/locales/de/LC_MESSAGES/collective.contentrules.mustread.po
src/collective/contentrules/mustread/locales/de/LC_MESSAGES/plone.po
src/collective/contentrules/mustread/profiles/default/actions.xml
src/collective/contentrules/mustread/profiles/default/browserlayer.xml
src/collective/contentrules/mustread/profiles/default/collectivecontentrulesmustread_default.txt
src/collective/contentrules/mustread/profiles/default/collectivecontentrulesmustread_marker.txt
