Metadata-Version: 1.1
Name: collective.contentrules.mustread
Version: 1.0a2
Summary: Define which users need to mark a content item as read (via collective.mustread)
Home-page: https://pypi.python.org/pypi/collective.contentrules.mustread
Author: Harald Friessnegger
Author-email: harald@webmeisterei.com
License: GPL version 2
Keywords: Python Plone
Platform: UNKNOWN
Classifier: Environment :: Web Environment
Classifier: Framework :: Plone
Classifier: Framework :: Plone :: 4.3
Classifier: Programming Language :: Python
Classifier: Programming Language :: Python :: 2.7
Classifier: Operating System :: OS Independent
Classifier: License :: OSI Approved :: GNU General Public License v2 (GPLv2)
